Metadata-Version: 1.0
Name: kindi
Version: 0.0.4
Summary: Kind incommunicados package for user secrets
Home-page: https://github.com/dicaso/kindi
Author: Christophe Van Neste
Author-email: beukueb@gmail.com
License: GNU GENERAL PUBLIC LICENSE
Platform: UNKNOWN
